{
  "required": true,
  "minVersion": "0.8",
  "package": "mizurin.shieldmod.mixins",
  "compatibilityLevel": "JAVA_8",
  "mixins": [
    "BlockFarmlandMixin",
    "ColorizerMixin",
    "DazedMixin",
    "FieldMixin",
    "KnockBackMixin",
    "ShieldMixin",
    "SpiderLabyrinthMixin",
    "WorldFeatureLabyrinthMixin",
    "WorldMixin",
    "client.BipedRendererMixin",
    "client.IconMixin",
    "client.LivingRendererMixin",
    "client.PaintingMixin",
    "client.PlayerRendererMixin",
    "client.SoundMixin",
    "entity.EntityCreeperMixin",
    "entity.EntityLivingMixin",
    "entity.EntitySkeletonMixin",
    "entity.EntitySnowManMixin",
    "entity.EntitySpiderMixin",
    "entity.EntityZombieArmoredMixin",
    "entity.SpiderWebMixin"
  ],
  "client": [
    "client.BipedRendererMixin",
    "client.LivingRendererMixin",
    "client.PaintingMixin",
    "client.PlayerRendererMixin",
    "client.SoundMixin"
  ],
  "injectors": {
    "defaultRequire": 1
  }
}
